Workbook

Sheet Before-After
A1: # | B1: Page URL | C1: Page ID | D1: Where | E1: Section | F1: Rule | G1: Before (current text) | H1: After (proposed) | I1: Note | J1: Sharad decision | K1: Sharad comment | L1: Raw before (for applying) | M1: Raw after (for applying)
A2: 1 | B2: https://gondaliyacpa.ca/accountant-for-masonry-contractors/ | C2: 50424 | D2: Visible | E2: Case study - what we did | F2: R1 | G2: applied the $500,000 Small Business Deduction so active income is taxed near 12.2%, filed the outstanding T5018 slips, and set brick, block and mortar as section 10 inventory. | H2: applied the $500,000 Small Business Deduction so active income is taxed near 11.2% (12.2% before July 1, 2026), filed the outstanding T5018 slips, and set brick, block and mortar as section 10 inventory. | I2: Case-study result stated without a date as the current SBD-taxed rate; treated as current. If Sharad dates this engagement before July 1, 2026, switch to R3 (leave). | L2: applied the $500,000 Small Business Deduction so active income is taxed near 12.2%, filed the outstanding T5018 slips, and set brick, block and mortar as section 10 inventory. | M2: applied the $500,000 Small Business Deduction so active income is taxed near 11.2% (12.2% before July 1, 2026), filed the outstanding T5018 slips, and set brick, block and mortar as section 10 inventory.
A3: 2 | B3: https://gondaliyacpa.ca/accountant-for-masonry-contractors/ | C3: 50424 | D3: Visible | E3: Case study - result | F3: R1 | G3: Active income taxed near the 12.2% small-business rate | H3: Active income taxed near the 11.2% small-business rate | I3: Case-study result stated without a date as the current SBD-taxed rate; treated as current. If Sharad dates this engagement before July 1, 2026, switch to R3 (leave). | L3: <li>Active income taxed near the 12.2% small-business rate</li> | M3: <li>Active income taxed near the 11.2% small-business rate</li>
A4: 3 | B4: https://gondaliyacpa.ca/fire-protection-contractor-tax-planning-canada/ | C4: 50370 | D4: Visible | E4: The Structure - Small Business Deduction | F4: R3 | G4: giving a blended provincial rate of roughly 2.7% for a calendar-year corporation and a combined rate near 11.7% rather than the 12.2% that applied before. | H4: giving a blended provincial rate of roughly 2.7% for a calendar-year corporation and a combined rate near 11.7% rather than the 12.2% that applied before. | I4: 12.2% is stated as the rate that applied before July 1, 2026; leave as is. | L4: giving a blended provincial rate of roughly 2.7% for a calendar-year corporation and a combined rate near 11.7% rather than the 12.2% that applied before.</p> | M4: giving a blended provincial rate of roughly 2.7% for a calendar-year corporation and a combined rate near 11.7% rather than the 12.2% that applied before.</p>
A5: 4 | B5: https://gondaliyacpa.ca/accountant-for-millwork-companies/ | C5: 50380 | D5: Visible | E5: Case study - what we did | F5: R1 | G5: applied the $500,000 Small Business Deduction so active income is taxed near 12.2%, set section 10 materials and work-in-progress inventory, and filed Schedule 31 for the apprenticeship credit. | H5: applied the $500,000 Small Business Deduction so active income is taxed near 11.2% (12.2% before July 1, 2026), set section 10 materials and work-in-progress inventory, and filed Schedule 31 for the apprenticeship credit. | I5: Case-study result stated without a date as the current SBD-taxed rate; treated as current. If Sharad dates this engagement before July 1, 2026, switch to R3 (leave). | L5: applied the $500,000 Small Business Deduction so active income is taxed near 12.2%, set section 10 materials and work-in-progress inventory, and filed Schedule 31 for the apprenticeship credit. | M5: applied the $500,000 Small Business Deduction so active income is taxed near 11.2% (12.2% before July 1, 2026), set section 10 materials and work-in-progress inventory, and filed Schedule 31 for the apprenticeship credit.
A6: 5 | B6: https://gondaliyacpa.ca/accountant-for-millwork-companies/ | C6: 50380 | D6: Visible | E6: Case study - result | F6: R1 | G6: Cut the combined tax bill materially at the 12.2% rate | H6: Cut the combined tax bill materially at the 11.2% rate | I6: Case-study result stated without a date as the current SBD-taxed rate; treated as current. If Sharad dates this engagement before July 1, 2026, switch to R3 (leave). | L6: <li>Cut the combined tax bill materially at the 12.2% rate</li> | M6: <li>Cut the combined tax bill materially at the 11.2% rate</li>
A7: 6 | B7: https://gondaliyacpa.ca/accountant-for-landscaping-companies/ | C7: 50379 | D7: Visible | E7: Case study - what we did | F7: R1 | G7: applied the $500,000 Small Business Deduction so active income is taxed near 12.2%, and set up the prepaid maintenance contracts as deferred revenue recognized across the season. | H7: applied the $500,000 Small Business Deduction so active income is taxed near 11.2% (12.2% before July 1, 2026), and set up the prepaid maintenance contracts as deferred revenue recognized across the season. | I7: Case-study result stated without a date as the current SBD-taxed rate; treated as current. If Sharad dates this engagement before July 1, 2026, switch to R3 (leave). | L7: applied the $500,000 Small Business Deduction so active income is taxed near 12.2%, and set up the prepaid maintenance contracts as deferred revenue recognized across the season. | M7: applied the $500,000 Small Business Deduction so active income is taxed near 11.2% (12.2% before July 1, 2026), and set up the prepaid maintenance contracts as deferred revenue recognized across the season.
A8: 7 | B8: https://gondaliyacpa.ca/accountant-for-landscaping-companies/ | C8: 50379 | D8: Visible | E8: Case study - result | F8: R1 | G8: Active income taxed near the 12.2% small-business rate | H8: Active income taxed near the 11.2% small-business rate | I8: Case-study result stated without a date as the current SBD-taxed rate; treated as current. If Sharad dates this engagement before July 1, 2026, switch to R3 (leave). | L8: <li>Active income taxed near the 12.2% small-business rate</li> | M8: <li>Active income taxed near the 11.2% small-business rate</li>
A9: 8 | B9: https://gondaliyacpa.ca/accountant-for-snow-removal-businesses/ | C9: 50377 | D9: Visible | E9: Case study - what we did | F9: R1 | G9: applied the $500,000 Small Business Deduction so active income is taxed near 12.2%, reclassified the loaders to Class 38 at 30% to recover the lost CCA, and filed the outstanding T5018 slips for every subcontracted route. | H9: applied the $500,000 Small Business Deduction so active income is taxed near 11.2% (12.2% before July 1, 2026), reclassified the loaders to Class 38 at 30% to recover the lost CCA, and filed the outstanding T5018 slips for every subcontracted route. | I9: Case-study result stated without a date as the current SBD-taxed rate; treated as current. If Sharad dates this engagement before July 1, 2026, switch to R3 (leave). | L9: applied the $500,000 Small Business Deduction so active income is taxed near 12.2%, reclassified the loaders to Class 38 at 30% to recover the lost CCA, and filed the outstanding T5018 slips for every subcontracted route. | M9: applied the $500,000 Small Business Deduction so active income is taxed near 11.2% (12.2% before July 1, 2026), reclassified the loaders to Class 38 at 30% to recover the lost CCA, and filed the outstanding T5018 slips for every subcontracted route.
A10: 9 | B10: https://gondaliyacpa.ca/accountant-for-snow-removal-businesses/ | C10: 50377 | D10: Visible | E10: Case study - result | F10: R1 | G10: Cut the combined tax bill materially at the 12.2% rate | H10: Cut the combined tax bill materially at the 11.2% rate | I10: Case-study result stated without a date as the current SBD-taxed rate; treated as current. If Sharad dates this engagement before July 1, 2026, switch to R3 (leave). | L10: <li>Cut the combined tax bill materially at the 12.2% rate</li> | M10: <li>Cut the combined tax bill materially at the 11.2% rate</li>
A11: 10 | B11: https://gondaliyacpa.ca/accountant-for-lawn-care-businesses/ | C11: 50375 | D11: Visible | E11: Case study - result | F11: R1 | G11: Cut the combined tax rate from personal levels toward 12.2% | H11: Cut the combined tax rate from personal levels toward 11.2% (12.2% before July 1, 2026) | I11: Case-study result stated without a date as the current SBD-taxed rate; treated as current. If Sharad dates this engagement before July 1, 2026, switch to R3 (leave). | L11: <li>Cut the combined tax rate from personal levels toward 12.2%</li> | M11: <li>Cut the combined tax rate from personal levels toward 11.2% (12.2% before July 1, 2026)</li>
A12: 11 | B12: https://gondaliyacpa.ca/clothing-store-year-end-accounting-canada/ | C12: 50309 | D12: Visible | E12: The Filing - Small Business Deduction | F12: R3 | G12: giving a combined rate near 11.7% rather than the 12.2% that applied before the change. | H12: giving a combined rate near 11.7% rather than the 12.2% that applied before the change. | I12: 12.2% is stated as the rate that applied before July 1, 2026; leave as is. | L12: giving a combined rate near 11.7% rather than the 12.2% that applied before the change. | M12: giving a combined rate near 11.7% rather than the 12.2% that applied before the change.
A13: 12 | B13: https://gondaliyacpa.ca/clothing-store-year-end-accounting-canada/ | C13: 50309 | D13: Visible | E13: Rates update note | F13: R3 | G13: giving a blended provincial rate of roughly 2.7% for a calendar-year corporation and a combined rate near 11.7% rather than the previous 12.2%. | H13: giving a blended provincial rate of roughly 2.7% for a calendar-year corporation and a combined rate near 11.7% rather than the previous 12.2%. | I13: 12.2% is stated as the rate that applied before July 1, 2026; leave as is. | L13: giving a blended provincial rate of roughly 2.7% for a calendar-year corporation and a combined rate near 11.7% rather than the previous 12.2%. | M13: giving a blended provincial rate of roughly 2.7% for a calendar-year corporation and a combined rate near 11.7% rather than the previous 12.2%.
... A80: 79 | B80: https://gondaliyacpa.ca/accounting-and-tax-services-for-small-businesses/ | C80: 45830 | D80: Visible | E80: Case study - results (Vaughan marketing agency) | F80: R4 | G80: Saved $5,005 in corporate tax | H80: Saved $5,355 in corporate tax | I80: Sharad to confirm figure. $5,005 = $35,000 x (26.5% - 12.2% = 14.3%), so the implied income kept under the limit is $35,000. At 11.2%: $35,000 x (26.5% - 11.2% = 15.3%) = $5,355. If the engagement predates July 1, 2026, leave both this and the 12.2% row as is. | L80: <li>Saved $5,005 in corporate tax</li> | M80: <li>Saved $5,355 in corporate tax</li>
A81: 80 | B81: https://gondaliyacpa.ca/should-i-buy-assets-personally-or-through-my-corporation/ | C81: 45409 | D81: Visible | E81: Quick Answer | F81: R1 | G81: Assets that earn business income belong in the corporation: bought with pre-tax dollars taxed near 12.2%, depreciated, HST recovered. | H81: Assets that earn business income belong in the corporation: bought with pre-tax dollars taxed near 11.2% (12.2% before July 1, 2026), depreciated, HST recovered. | L81: Assets that earn business income belong in the corporation: bought with pre-tax dollars taxed near 12.2%, depreciated, HST recovered. | M81: Assets that earn business income belong in the corporation: bought with pre-tax dollars taxed near 11.2% (12.2% before July 1, 2026), depreciated, HST recovered.
A82: 81 | B82: https://gondaliyacpa.ca/should-i-buy-assets-personally-or-through-my-corporation/ | C82: 45409 | D82: Visible | E82: Investments: The Deferral and Its Two Prices | F82: R1 | G82: money that would have shrunk past 53% on the way out instead compounds from a base taxed near 12.2%. | H82: money that would have shrunk past 53% on the way out instead compounds from a base taxed near 11.2%. | L82: money that would have shrunk past 53% on the way out instead compounds from a base taxed near 12.2%. | M82: money that would have shrunk past 53% on the way out instead compounds from a base taxed near 11.2%.
A83: 82 | B83: https://gondaliyacpa.ca/should-i-buy-assets-personally-or-through-my-corporation/ | C83: 45409 | D83: Visible | E83: FAQ - Why do people say corporate dollars are cheaper? | F83: R1 + R4 | G83: Because the corporation keeps roughly 87.8 cents of each active dollar after the small business rate of about 12.2%, while a top-bracket owner keeps under 47 cents after personal tax above 53%. | H83: Because the corporation keeps roughly 88.8 cents of each active dollar after the small business rate of about 11.2%, while a top-bracket owner keeps under 47 cents after personal tax above 53%. | I83: R4: 87.8 cents = 100 - 12.2; at 11.2% it is 100 - 11.2 = 88.8 cents. Sharad to confirm figure. | L83: Because the corporation keeps roughly 87.8 cents of each active dollar after the small business rate of about 12.2%, while a top-bracket owner keeps under 47 cents after personal tax above 53%. | M83: Because the corporation keeps roughly 88.8 cents of each active dollar after the small business rate of about 11.2%, while a top-bracket owner keeps under 47 cents after personal tax above 53%.
A84: 83 | B84: https://gondaliyacpa.ca/should-i-buy-assets-personally-or-through-my-corporation/ | C84: 45409 | D84: JSON-LD | E84: FAQ schema - Why do people say corporate dollars are cheaper? | F84: R1 + R4 | G84: Because the corporation keeps roughly 87.8 cents of each active dollar after the small business rate of about 12.2%, while a top-bracket owner keeps under 47 cents after personal tax above 53%. | H84: Because the corporation keeps roughly 88.8 cents of each active dollar after the small business rate of about 11.2%, while a top-bracket owner keeps under 47 cents after personal tax above 53%. | I84: JSON-LD copy, in _elementor_data only. R4: 100 - 11.2 = 88.8 cents. Sharad to confirm figure. | L84: "text":"Because the corporation keeps roughly 87.8 cents of each active dollar after the small business rate of about 12.2%, while a top-bracket owner keeps under 47 cents after personal tax above 53%. | M84: "text":"Because the corporation keeps roughly 88.8 cents of each active dollar after the small business rate of about 11.2%, while a top-bracket owner keeps under 47 cents after personal tax above 53%.
A85: 84 | B85: https://gondaliyacpa.ca/should-i-buy-assets-personally-or-through-my-corporation/ | C85: 45409 | D85: Visible | E85: FAQ - How do the corporate tax rates figure into all this? | F85: R1 | G85: They are the engine of the whole question: the gap between roughly 12.2% on the first $500,000 of active income and personal rates above 53% is what makes corporate dollars cheaper | H85: They are the engine of the whole question: the gap between roughly 11.2% on the first $500,000 of active income and personal rates above 53% is what makes corporate dollars cheaper | L85: They are the engine of the whole question: the gap between roughly 12.2% on the first $500,000 of active income and personal rates above 53% is what makes corporate dollars cheaper | M85: They are the engine of the whole question: the gap between roughly 11.2% on the first $500,000 of active income and personal rates above 53% is what makes corporate dollars cheaper
A86: 85 | B86: https://gondaliyacpa.ca/should-i-buy-assets-personally-or-through-my-corporation/ | C86: 45409 | D86: JSON-LD | E86: FAQ schema - How do the corporate tax rates figure into all this? | F86: R1 | G86: They are the engine of the whole question: the gap between roughly 12.2% on the first $500,000 of active income and personal rates above 53% is what makes corporate dollars cheaper | H86: They are the engine of the whole question: the gap between roughly 11.2% on the first $500,000 of active income and personal rates above 53% is what makes corporate dollars cheaper | I86: JSON-LD copy, in _elementor_data only. | L86: "text":"They are the engine of the whole question: the gap between roughly 12.2% on the first $500,000 of active income and personal rates above 53% is what makes corporate dollars cheaper | M86: "text":"They are the engine of the whole question: the gap between roughly 11.2% on the first $500,000 of active income and personal rates above 53% is what makes corporate dollars cheaper
A87: 86 | B87: https://gondaliyacpa.ca/medical-professional-corporations-mpc-passive-income-tosi-rules/ | C87: 45030 | D87: Visible | E87: The passive income grind section | F87: R1 | G87: that active practice income is taxed at the general rate of about 26.5% in Ontario instead of the low 12.2%. | H87: that active practice income is taxed at the general rate of about 26.5% in Ontario instead of the low 11.2% (12.2% before July 1, 2026). | L87: that active practice income is taxed at the general rate of about 26.5% in Ontario instead of the low 12.2%. | M87: that active practice income is taxed at the general rate of about 26.5% in Ontario instead of the low 11.2% (12.2% before July 1, 2026).
A88: 87 | B88: https://gondaliyacpa.ca/medical-professional-corporations-mpc-passive-income-tosi-rules/ | C88: 45030 | D88: Visible | E88: FAQ - What happens to my tax rate if I lose the small business deduction? | F88: R1 | G88: The active income that would have been taxed at the low combined rate of about 12.2% in Ontario is instead taxed at the general rate | H88: The active income that would have been taxed at the low combined rate of about 11.2% in Ontario is instead taxed at the general rate | L88: The active income that would have been taxed at the low combined rate of about 12.2% in Ontario is instead taxed at the general rate | M88: The active income that would have been taxed at the low combined rate of about 11.2% in Ontario is instead taxed at the general rate
A89: 88 | B89: https://gondaliyacpa.ca/medical-professional-corporations-mpc-passive-income-tosi-rules/ | C89: 45030 | D89: JSON-LD | E89: FAQ schema - What happens to my tax rate if I lose the small business deduction? | F89: R1 | G89: The active income that would have been taxed at the low combined rate of about 12.2% in Ontario is instead taxed at the general rate | H89: The active income that would have been taxed at the low combined rate of about 11.2% in Ontario is instead taxed at the general rate | I89: JSON-LD copy, in _elementor_data only. | L89: "text":"The active income that would have been taxed at the low combined rate of about 12.2% in Ontario is instead taxed at the general rate | M89: "text":"The active income that would have been taxed at the low combined rate of about 11.2% in Ontario is instead taxed at the general rate
A90: 89 | B90: https://gondaliyacpa.ca/small-business-accounting-services/ | C90: 44973 | D90: Visible | E90: 2026 rate table - row to June 30, 2026 | F90: R3 | G90: First $500,000 active income (to June 30, 2026)12.2%3.2% provincial + 9% federal, with the Small Business Deduction | H90: First $500,000 active income (to June 30, 2026)12.2%3.2% provincial + 9% federal, with the Small Business Deduction | I90: Both 12.2% and 3.2% are tied to income to June 30, 2026; leave. In _elementor_data this row is <tr class="dp-hl"> (highlighted); Sharad may want the highlight moved to the July 1, 2026 row. | L90: <td>First $500,000 active income (to June 30, 2026)</td><td>12.2%</td><td>3.2% provincial + 9% federal, with the Small Business Deduction</td> | M90: <td>First $500,000 active income (to June 30, 2026)</td><td>12.2%</td><td>3.2% provincial + 9% federal, with the Small Business Deduction</td>
A91: 90 | B91: https://gondaliyacpa.ca/small-business-accounting-services/ | C91: 44973 | D91: Visible | E91: FAQ - What tax rate does my small corporation pay in Ontario? | F91: R1 + R2 | G91: A qualifying Ontario CCPC pays a combined 12.2% on the first $500,000 of active business income, made up of 3.2% provincial and 9% federal. | H91: A qualifying Ontario CCPC pays a combined 11.2% (12.2% before July 1, 2026) on the first $500,000 of active business income, made up of 2.2% (3.2% before July 1, 2026) provincial and 9% federal. | I91: Stated as the current rate. The next sentence ('On July 1, 2026 the provincial rate drops to 2.2%, bringing the combined rate to 11.2%.') becomes redundant after this change; Sharad may want to delete it. | L91: A qualifying Ontario CCPC pays a combined 12.2% on the first $500,000 of active business income, made up of 3.2% provincial and 9% federal. | M91: A qualifying Ontario CCPC pays a combined 11.2% (12.2% before July 1, 2026) on the first $500,000 of active business income, made up of 2.2% (3.2% before July 1, 2026) provincial and 9% federal.
A92: 91 | B92: https://gondaliyacpa.ca/small-business-accounting-services/ | C92: 44973 | D92: JSON-LD | E92: FAQ schema - What tax rate does my small corporation pay in Ontario? | F92: R1 + R2 | G92: A qualifying Ontario CCPC pays a combined 12.2% on the first $500,000 of active business income, made up of 3.2% provincial and 9% federal. | H92: A qualifying Ontario CCPC pays a combined 11.2% (12.2% before July 1, 2026) on the first $500,000 of active business income, made up of 2.2% (3.2% before July 1, 2026) provincial and 9% federal. | I92: JSON-LD copy, in _elementor_data only. Same redundant-next-sentence note as the visible FAQ. | L92: "text":"A qualifying Ontario CCPC pays a combined 12.2% on the first $500,000 of active business income, made up of 3.2% provincial and 9% federal. | M92: "text":"A qualifying Ontario CCPC pays a combined 11.2% (12.2% before July 1, 2026) on the first $500,000 of active business income, made up of 2.2% (3.2% before July 1, 2026) provincial and 9% federal.

Sheet URLs
A1: # | B1: Page URL | C1: Page ID | D1: Title | E1: Rows to review | F1: Rows to change | G1: Note
A2: 1 | B2: https://gondaliyacpa.ca/accountant-for-masonry-contractors/ | C2: 50424 | D2: Accounting and Tax Services for Masonry Contractors | E2: =COUNTIF('Before-After'!$C:$C,C2) -> 2 | F2: =COUNTIFS('Before-After'!$C:$C,C2,'Before-After'!$F:$F,"<>R3") -> 2 | G2: Other rate mentions (tax planning, incorporation, FAQs and JSON-LD) already show 11.2%. '$600,000 file' in the T2 card is a revenue example, not the small business limit - no change.
A3: 2 | B3: https://gondaliyacpa.ca/fire-protection-contractor-tax-planning-canada/ | C3: 50370 | D3: How Fire Protection Contractors in Canada Can Reduce Taxes and Improve Cash Flow With Strategic Tax Planning | E3: =COUNTIF('Before-After'!$C:$C,C3) -> 1 | F3: =COUNTIFS('Before-After'!$C:$C,C3,'Before-After'!$F:$F,"<>R3") -> 0 | G3: Post already reflects the July 1, 2026 change (2.2% / 11.2% / blended 11.7% current; 12.2% only as the former rate). No changes needed. No 3.2%, 0.122/0.032 or $600,000/$600K found. Fetched as post_type "posts".
A4: 3 | B4: https://gondaliyacpa.ca/accountant-for-millwork-companies/ | C4: 50380 | D4: Accounting and Tax Services for Millwork Companies | E4: =COUNTIF('Before-After'!$C:$C,C4) -> 2 | F4: =COUNTIFS('Before-After'!$C:$C,C4,'Before-After'!$F:$F,"<>R3") -> 2 | G4: Other rate mentions (service cards, FAQs and JSON-LD) already show 11.2%. No 3.2%, 0.122/0.032, $600,000/$600K or 12.2%-derived dollar figures found.
A5: 4 | B5: https://gondaliyacpa.ca/accountant-for-landscaping-companies/ | C5: 50379 | D5: Accounting and Tax Services for Landscaping Companies | E5: =COUNTIF('Before-After'!$C:$C,C5) -> 2 | F5: =COUNTIFS('Before-After'!$C:$C,C5,'Before-After'!$F:$F,"<>R3") -> 2 | G5: Other rate mentions (service cards, FAQs and JSON-LD) already show 11.2%. No 3.2%, 0.122/0.032, $600,000/$600K or 12.2%-derived dollar figures found.
A6: 5 | B6: https://gondaliyacpa.ca/accountant-for-snow-removal-businesses/ | C6: 50377 | D6: Accounting and Tax Services for Snow Removal Businesses | E6: =COUNTIF('Before-After'!$C:$C,C6) -> 2 | F6: =COUNTIFS('Before-After'!$C:$C,C6,'Before-After'!$F:$F,"<>R3") -> 2 | G6: Other rate mentions (service cards, FAQs and JSON-LD) already show 11.2%. No 3.2%, 0.122/0.032, $600,000/$600K or 12.2%-derived dollar figures found.
A7: 6 | B7: https://gondaliyacpa.ca/accountant-for-lawn-care-businesses/ | C7: 50375 | D7: Accounting and Tax Services for Lawn Care Businesses | E7: =COUNTIF('Before-After'!$C:$C,C7) -> 1 | F7: =COUNTIFS('Before-After'!$C:$C,C7,'Before-After'!$F:$F,"<>R3") -> 1 | G7: Other rate mentions (service cards, FAQs and JSON-LD) already show 11.2%. No 3.2%, 0.122/0.032 or 12.2%-derived dollar figures found. '$600,000 operation' in the incorporation card is a business-sale value, not the small business limit - no change.
A8: 7 | B8: https://gondaliyacpa.ca/clothing-store-year-end-accounting-canada/ | C8: 50309 | D8: Clothing Store Year-End Accounting Checklist: How to Prepare Your Retail Business for Corporate Tax Filing in Canada | E8: =COUNTIF('Before-After'!$C:$C,C8) -> 2 | F8: =COUNTIFS('Before-After'!$C:$C,C8,'Before-After'!$F:$F,"<>R3") -> 0 | G8: Post already reflects the July 1, 2026 change (2.2% / 11.2% / blended 11.7% current; 12.2% only as the former rate). No changes needed. No 3.2%, 0.122/0.032 or $600,000/$600K found. Fetched as post_type "posts".
A9: 8 | B9: https://gondaliyacpa.ca/accountant-for-garage-door-companies/ | C9: 50247 | D9: Accounting and Tax Services for Garage Door Companies | E9: =COUNTIF('Before-After'!$C:$C,C9) -> 2 | F9: =COUNTIFS('Before-After'!$C:$C,C9,'Before-After'!$F:$F,"<>R3") -> 2 | G9: Other rate mentions (service cards, FAQs and JSON-LD) already show 11.2%. No 3.2%, 0.122/0.032, $600,000/$600K or 12.2%-derived dollar figures found.
A10: 9 | B10: https://gondaliyacpa.ca/accountant-for-insulation-contractors/ | C10: 50245 | D10: Accounting and Tax Services for Insulation Contractors | E10: =COUNTIF('Before-After'!$C:$C,C10) -> 1 | F10: =COUNTIFS('Before-After'!$C:$C,C10,'Before-After'!$F:$F,"<>R3") -> 1 | G10: Other rate mentions (service cards, FAQs and JSON-LD) already show 11.2%. No 3.2%, 0.122/0.032 or 12.2%-derived dollar figures found. No $600,000/$600K found.
A11: 10 | B11: https://gondaliyacpa.ca/accountant-for-fire-protection-contractors/ | C11: 50243 | D11: Accounting and Tax Services for Fire Protection Contractors | E11: =COUNTIF('Before-After'!$C:$C,C11) -> 1 | F11: =COUNTIFS('Before-After'!$C:$C,C11,'Before-After'!$F:$F,"<>R3") -> 1 | G11: Other rate mentions (service cards, FAQs and JSON-LD) already show 11.2%. No 3.2%, 0.122/0.032 or 12.2%-derived dollar figures found. No $600,000/$600K found. Case-study '$27,000 a year' saving is not shown as computed from 12.2% - left as is.
A12: 11 | B12: https://gondaliyacpa.ca/accountant-for-clothing-stores/ | C12: 50186 | D12: Accounting and Tax Services for Clothing Stores | E12: =COUNTIF('Before-After'!$C:$C,C12) -> 2 | F12: =COUNTIFS('Before-After'!$C:$C,C12,'Before-After'!$F:$F,"<>R3") -> 2 | G12: No JSON-LD or meta occurrences; no R4 dollar figures computed from 12.2%.
A13: 12 | B13: https://gondaliyacpa.ca/accountant-for-shoe-stores/ | C13: 50183 | D13: Accounting and Tax Services for Shoe Stores | E13: =COUNTIF('Before-After'!$C:$C,C13) -> 2 | F13: =COUNTIFS('Before-After'!$C:$C,C13,'Before-After'!$F:$F,"<>R3") -> 2 | G13: No JSON-LD or meta occurrences; no R4 dollar figures computed from 12.2%.
... A51: 50 | B51: https://gondaliyacpa.ca/small-business-accounting-services/ | C51: 44973 | D51: Small Business Accounting Services | E51: =COUNTIF('Before-After'!$C:$C,C51) -> 3 | F51: =COUNTIFS('Before-After'!$C:$C,C51,'Before-After'!$F:$F,"<>R3") -> 2 | G51: Elementor page: the live source is the _elementor_data post meta (widget 'html'); post_content is a stripped fallback copy. Visible 'before' strings are exact, unique substrings of post_content and also occur in the decoded _elementor_data html; the JSON-LD FAQPage copy exists only in _elementor_data (decoded), and its 'before' strings are verified unique there. Apply the edits to _elementor_data, not just post_content. No 0.122, 0.032 or $600K.
D52: Total | E52: =SUM(E2:E51) -> 91 | F52: =SUM(F2:F51) -> 80

Sheet Rules
A1: Rule | B1: Where the figure appears | C1: Action
A2: R1 | B2: 12.2% stated as the current combined Ontario small business rate | C2: Change to 11.2% and add "(12.2% before July 1, 2026)" once per page
A3: R2 | B3: 3.2% stated as the current Ontario small business rate | C3: Change to 2.2% and add "(3.2% before July 1, 2026)" once per page
A4: R3 | B4: 12.2% or 3.2% tied to 2025 or earlier, or to income before July 1, 2026 | C4: Leave as is
A5: R4 | B5: Dollar figure worked out from 12.2% | C5: Recalculate at 11.2%; Sharad confirms the figure
A6: R5 | B6: Example for a December 31, 2026 year-end | C6: Use the blended 11.70%
A7: R6 | B7: Calculator code with 0.122 or 0.032 | C7: Replace with the day-prorated logic from the page 7 calculator
A8: R7 | B8: Small business limit shown as $600,000 | C8: Change to $500,000
A10: Rate correction batch 2 of about 8 (50 URLs), prepared October 23, 2026 for Sharad's review. Source: Sharad's Existing Page Fixes and Rate Correction Rules (PSB package, Oct 3, 2026).
A11: How to review: in the Before-After tab, choose Approve, Change or Reject in the yellow 'Sharad decision' column. Use 'Sharad comment' for any change.
A12: Example: decision 'Change', comment 'Use 11.2% but drop the (12.2% before July 1, 2026) note here'.
A13: Grey rows are R3 (historical figures): proposed to stay as they are.
A14: Every visible FAQ change has a matching JSON-LD row so the schema stays identical to the page.
A15: Nothing on the website changes until Sharad approves the batch.
